ilyasfamily/__init__.py
ilyasfamily/core.py
ilyasfamily/types.py
ilyasfamily-0.1.0.dist-info/licenses/LICENSE
ilyasfamily-0.1.0.dist-info/METADATA
ilyasfamily-0.1.0.dist-info/WHEEL
ilyasfamily-0.1.0.dist-info/top_level.txt
ilyasfamily-0.1.0.dist-info/RECORD
