Metadata-Version: 2.4
Name: ilyasfamily
Version: 0.1.0
Summary: Python implementation of IlyasFamily data format
Author-email: Nazwa Shabrina Zain <nazwagodean@gmail.com>
License: Apache-2.0
Project-URL: Homepage, https://github.com/aflacake/ilyasfamily-py
Project-URL: Documentation, https://github.com/aflacake/ilyasfamily-spec
Keywords: data-format,json-alternative,ilyasfamily
Classifier: Programming Language :: Python :: 3
Classifier: License :: OSI Approved :: Apache Software License
Classifier: Operating System :: OS Independent
Requires-Python: >=3.8
License-File: LICENSE
Dynamic: license-file
